[
  {
    "id": 1,
    "name": "Rachel Shannon",
    "email": "bbrown@taylor.com",
    "age": 60,
    "country": "Tajikistan",
    "isActive": true,
    "registered": "2021-01-04"
  },
  {
    "id": 2,
    "name": "Chelsey Rodriguez",
    "email": "david35@yahoo.com",
    "age": 22,
    "country": "United Arab Emirates",
    "isActive": true,
    "registered": "2021-02-03"
  },
  {
    "id": 3,
    "name": "Jason Holloway",
    "email": "tinadavis@riley.com",
    "age": 57,
    "country": "Austria",
    "isActive": true,
    "registered": "2023-08-16"
  },
  {
    "id": 4,
    "name": "Christopher Beck",
    "email": "lopezerica@stewart-nguyen.net",
    "age": 61,
    "country": "Trinidad and Tobago",
    "isActive": true,
    "registered": "2024-12-16"
  },
  {
    "id": 5,
    "name": "Robert Adams",
    "email": "johnray@yahoo.com",
    "age": 30,
    "country": "Saint Pierre and Miquelon",
    "isActive": true,
    "registered": "2022-09-15"
  },
  {
    "id": 6,
    "name": "Kevin Wise",
    "email": "hjackson@quinn.org",
    "age": 39,
    "country": "Somalia",
    "isActive": false,
    "registered": "2025-06-04"
  },
  {
    "id": 7,
    "name": "Jonathan Garza",
    "email": "ycuevas@gmail.com",
    "age": 20,
    "country": "Bosnia and Herzegovina",
    "isActive": true,
    "registered": "2022-02-05"
  },
  {
    "id": 8,
    "name": "Jo Mann",
    "email": "michael95@gmail.com",
    "age": 40,
    "country": "Montserrat",
    "isActive": true,
    "registered": "2022-09-29"
  },
  {
    "id": 9,
    "name": "Jesus Logan",
    "email": "zrodriguez@johnson.com",
    "age": 49,
    "country": "Bahrain",
    "isActive": true,
    "registered": "2025-06-02"
  },
  {
    "id": 10,
    "name": "Daryl Brown",
    "email": "erin40@juarez.com",
    "age": 62,
    "country": "Russian Federation",
    "isActive": true,
    "registered": "2024-08-17"
  },
  {
    "id": 11,
    "name": "Robin Johnson",
    "email": "teresaburns@morrison.com",
    "age": 49,
    "country": "Turks and Caicos Islands",
    "isActive": false,
    "registered": "2022-08-03"
  },
  {
    "id": 12,
    "name": "Samantha Ruiz MD",
    "email": "audrey94@yahoo.com",
    "age": 33,
    "country": "Martinique",
    "isActive": true,
    "registered": "2022-02-18"
  },
  {
    "id": 13,
    "name": "Courtney Larson",
    "email": "rushdylan@gmail.com",
    "age": 65,
    "country": "Iraq",
    "isActive": false,
    "registered": "2021-02-25"
  },
  {
    "id": 14,
    "name": "Sharon Knight",
    "email": "philip46@gutierrez-johnson.com",
    "age": 46,
    "country": "Turkmenistan",
    "isActive": false,
    "registered": "2021-07-19"
  },
  {
    "id": 15,
    "name": "Renee Butler",
    "email": "daniel46@richards.net",
    "age": 33,
    "country": "Greenland",
    "isActive": true,
    "registered": "2025-03-10"
  },
  {
    "id": 16,
    "name": "Nicole Leon",
    "email": "nparker@patterson.com",
    "age": 45,
    "country": "Mongolia",
    "isActive": true,
    "registered": "2022-03-16"
  },
  {
    "id": 17,
    "name": "Christina Smith",
    "email": "kelly08@gmail.com",
    "age": 51,
    "country": "Uzbekistan",
    "isActive": true,
    "registered": "2021-01-03"
  },
  {
    "id": 18,
    "name": "David Barnes",
    "email": "erikstevens@mendez-wood.com",
    "age": 44,
    "country": "Myanmar",
    "isActive": false,
    "registered": "2022-04-14"
  },
  {
    "id": 19,
    "name": "Patricia Powell",
    "email": "timothy03@hotmail.com",
    "age": 23,
    "country": "Korea",
    "isActive": true,
    "registered": "2023-07-10"
  },
  {
    "id": 20,
    "name": "Joanna Mills",
    "email": "shannon70@johnson.net",
    "age": 63,
    "country": "Saint Vincent and the Grenadines",
    "isActive": false,
    "registered": "2022-08-23"
  },
  {
    "id": 21,
    "name": "Aaron Henderson",
    "email": "charlessusan@yahoo.com",
    "age": 60,
    "country": "Malawi",
    "isActive": true,
    "registered": "2023-09-28"
  },
  {
    "id": 22,
    "name": "Jacqueline Bush",
    "email": "jonesarthur@yahoo.com",
    "age": 31,
    "country": "Korea",
    "isActive": false,
    "registered": "2024-05-17"
  },
  {
    "id": 23,
    "name": "Thomas Fisher",
    "email": "travislopez@yahoo.com",
    "age": 56,
    "country": "Ecuador",
    "isActive": false,
    "registered": "2024-02-06"
  },
  {
    "id": 24,
    "name": "Thomas Lopez",
    "email": "kennethhenry@gmail.com",
    "age": 33,
    "country": "Gambia",
    "isActive": true,
    "registered": "2022-12-21"
  },
  {
    "id": 25,
    "name": "Bradley Olson",
    "email": "nicoledavis@little-aguilar.com",
    "age": 49,
    "country": "Sierra Leone",
    "isActive": false,
    "registered": "2020-09-13"
  },
  {
    "id": 26,
    "name": "Ivan Camacho",
    "email": "moniquemontoya@jackson.com",
    "age": 36,
    "country": "United Kingdom",
    "isActive": true,
    "registered": "2024-10-18"
  },
  {
    "id": 27,
    "name": "Joseph Houston",
    "email": "david46@walton.com",
    "age": 59,
    "country": "Suriname",
    "isActive": false,
    "registered": "2025-02-14"
  },
  {
    "id": 28,
    "name": "Jason Bennett",
    "email": "ktorres@hotmail.com",
    "age": 20,
    "country": "Austria",
    "isActive": false,
    "registered": "2021-04-19"
  },
  {
    "id": 29,
    "name": "Johnny Morris",
    "email": "nicholashayes@wise.info",
    "age": 25,
    "country": "Ghana",
    "isActive": false,
    "registered": "2024-06-28"
  },
  {
    "id": 30,
    "name": "Daniel Snyder",
    "email": "jacobwilson@gmail.com",
    "age": 49,
    "country": "Germany",
    "isActive": false,
    "registered": "2024-04-25"
  },
  {
    "id": 31,
    "name": "Jeffrey Lowery",
    "email": "mcleanmichael@stewart.com",
    "age": 32,
    "country": "Djibouti",
    "isActive": true,
    "registered": "2023-04-06"
  },
  {
    "id": 32,
    "name": "Ashley Cantu",
    "email": "lsimpson@gmail.com",
    "age": 31,
    "country": "Liberia",
    "isActive": false,
    "registered": "2024-12-30"
  },
  {
    "id": 33,
    "name": "Morgan Mcbride",
    "email": "hbridges@hotmail.com",
    "age": 54,
    "country": "Northern Mariana Islands",
    "isActive": true,
    "registered": "2022-03-26"
  },
  {
    "id": 34,
    "name": "Edward Luna",
    "email": "davischristina@lambert.org",
    "age": 46,
    "country": "Djibouti",
    "isActive": true,
    "registered": "2023-05-13"
  },
  {
    "id": 35,
    "name": "Janice Ortega",
    "email": "susan41@gmail.com",
    "age": 58,
    "country": "Guernsey",
    "isActive": false,
    "registered": "2021-05-30"
  },
  {
    "id": 36,
    "name": "Michelle Graves",
    "email": "ewright@hotmail.com",
    "age": 49,
    "country": "Spain",
    "isActive": false,
    "registered": "2023-07-30"
  },
  {
    "id": 37,
    "name": "Jesus Munoz",
    "email": "lisalewis@nguyen.biz",
    "age": 37,
    "country": "Antigua and Barbuda",
    "isActive": true,
    "registered": "2024-01-06"
  },
  {
    "id": 38,
    "name": "Monique Hall",
    "email": "obradley@james.com",
    "age": 49,
    "country": "Belize",
    "isActive": true,
    "registered": "2025-04-13"
  },
  {
    "id": 39,
    "name": "Kimberly White",
    "email": "monica68@stewart.com",
    "age": 38,
    "country": "Japan",
    "isActive": false,
    "registered": "2020-08-17"
  },
  {
    "id": 40,
    "name": "Molly Stevens",
    "email": "bradleykim@lopez.info",
    "age": 49,
    "country": "Central African Republic",
    "isActive": false,
    "registered": "2025-01-25"
  },
  {
    "id": 41,
    "name": "Madison Clayton",
    "email": "kevinsilva@valdez.com",
    "age": 19,
    "country": "Antigua and Barbuda",
    "isActive": true,
    "registered": "2020-08-04"
  },
  {
    "id": 42,
    "name": "Matthew Campbell",
    "email": "dustinsanchez@gmail.com",
    "age": 59,
    "country": "Suriname",
    "isActive": false,
    "registered": "2022-02-04"
  },
  {
    "id": 43,
    "name": "George Moore",
    "email": "denise50@hotmail.com",
    "age": 25,
    "country": "Bosnia and Herzegovina",
    "isActive": false,
    "registered": "2023-12-19"
  },
  {
    "id": 44,
    "name": "Clarence Barnes",
    "email": "vdaniel@campbell.com",
    "age": 51,
    "country": "American Samoa",
    "isActive": true,
    "registered": "2023-11-27"
  },
  {
    "id": 45,
    "name": "Matthew Bennett",
    "email": "tammy10@nielsen.com",
    "age": 36,
    "country": "Libyan Arab Jamahiriya",
    "isActive": false,
    "registered": "2025-04-24"
  },
  {
    "id": 46,
    "name": "Mrs. Rebecca Taylor",
    "email": "asmith@gmail.com",
    "age": 54,
    "country": "Western Sahara",
    "isActive": false,
    "registered": "2024-07-06"
  },
  {
    "id": 47,
    "name": "Michelle Camacho",
    "email": "okirby@gmail.com",
    "age": 37,
    "country": "Tokelau",
    "isActive": false,
    "registered": "2024-10-13"
  },
  {
    "id": 48,
    "name": "Ernest Werner",
    "email": "nduarte@yu-price.net",
    "age": 63,
    "country": "Sierra Leone",
    "isActive": false,
    "registered": "2025-02-23"
  },
  {
    "id": 49,
    "name": "Michelle Atkinson",
    "email": "jasonwilliams@galvan.biz",
    "age": 60,
    "country": "Zimbabwe",
    "isActive": true,
    "registered": "2022-02-26"
  },
  {
    "id": 50,
    "name": "Jennifer Wallace",
    "email": "allendominique@yahoo.com",
    "age": 62,
    "country": "Guinea-Bissau",
    "isActive": false,
    "registered": "2021-03-17"
  }
]